[
	{
		"symbol": "-",
		"precedence": 2,
		"description": "Minus",
		"unary": {
			"name": "Negative",
			"description": "Negates the operand's value"
		}
	},
	{
		"symbol": "*",
		"precedence": 4,
		"name": "Multiply",
		"description": "Multiply"
	},
	{
		"symbol": "*=",
		"precedence": 1,
		"description": "Contains"
	},
	{
		"symbol": "$=",
		"precedence": 1,
		"description": "Ends with"
	},
	{
		"symbol": "^=",
		"precedence": 1,
		"description": "Starts with"
	},
	{
		"symbol": "~=",
		"precedence": 1,
		"description": "Contains white-space-deliminited match to"
	},
	{
		"symbol": "/",
		"precedence": 4,
		"description": "Division"
	},
	{
		"symbol": "+",
		"unary": {
			"name": "Convert-to-number",
			"description": "Converts its operand's value to a number or NaN"
		},
		"precedence": 3,
		"name": "Add",
		"description": "Add"
	},
	{
		"symbol": "=",
		"precedence": 1,
		"types": "bool",
		"description": "Equality comparison"
	},
	{
		"symbol": "<",
		"precedence": 1,
		"types": "bool",
		"description": "Less than"
	},
	{
		"symbol": "<=",
		"precedence": 1,
		"types": "bool",
		"description": "Less than or equal"
	},
	{
		"symbol": ">",
		"precedence": 1,
		"types": "bool",
		"description": "Greater than"
	},
	{
		"symbol": ">=",
		"precedence": 1,
		"types": "bool",
		"description": "Greater than or equal"
	},
	{
		"symbol": "and",
		"precedence": 1,
		"description": "Logical AND"
	},
	{
		"symbol": "not",
		"unary": {
			"description": "Logical NOT"
		},
		"precedence": 0,
		"description": "Logical NOT"
	}
]