[
	{
		"url": "content/help/procedures/animation.setup.html",
		"name": "animation.setup",
		"id": "animation.setup"
	},
	{
		"url": "content/help/procedures/animation.snapshotstyle.html",
		"name": "animation.snapshotStyle",
		"id": "animation.snapshotstyle"
	},
	{
		"url": "content/help/properties/animationDuration.html",
		"name": "Animation Duration",
		"id": "animationduration"
	},
	{
		"url": "content/help/properties/animationTime.html",
		"name": "Animation Time",
		"id": "animationtime"
	},
	{
		"url": "content/help/features/assets.html",
		"name": "Assets",
		"id": "assets"
	},
	{
		"url": "content/help/features/auto-fix-code.html",
		"name": "Auto-fix Code",
		"id": "autofixcode"
	},
	{
		"url": "content/help/features/auto-run.html",
		"name": "Auto-Run",
		"id": "autorun"
	},
	{
		"url": "content/help/features/breakpoint.html",
		"name": "Breakpoints",
		"id": "breakpoint"
	},
	{
		"url": "content/help/features/code-editor.html",
		"name": "Code Editor",
		"id": "code-editor"
	},
	{
		"url": "content/help/features/commander.html",
		"name": "Commander",
		"id": "commander"
	},
	{
		"url": "content/help/features/debugger.html",
		"name": "Debugger",
		"id": "debugger"
	},
	{
		"url": "content/help/features/file-load-example.html",
		"name": "File Load Example",
		"id": "file-load-example"
	},
	{
		"url": "content/help/properties/fillColor.html",
		"name": "Shape Fill Color",
		"id": "fillcolor"
	},
	{
		"url": "content/help/differences-from-fms-logo.html",
		"name": "FMSLogo Comparison",
		"id": "fms-logo-comparison"
	},
	{
		"url": "content/help/features/format-code.html",
		"name": "Format Code",
		"id": "formatcode"
	},
	{
		"url": "content/help/features/graphics-screen.html",
		"name": "Graphics Screen",
		"id": "graphics-screen"
	},
	{
		"url": "content/help/features/image-exporter.html",
		"name": "Image Exporter",
		"id": "image-exporter"
	},
	{
		"url": "content/help/features/intermediateCodeExplorer.html",
		"name": "Intermediate Code Explorer",
		"id": "intermediatecode"
	},
	{
		"url": "content/help/properties/lineCap.html",
		"name": "Line Cap",
		"id": "line-cap"
	},
	{
		"url": "content/help/properties/lineJoinStyle.html",
		"name": "Line Join Style",
		"id": "line-join-style"
	},
	{
		"url": "content/help/features/parseTreeExplorer.html",
		"name": "Parse Tree Explorer",
		"id": "parsetree"
	},
	{
		"url": "content/help/properties/penColor.html",
		"name": "Pen Color",
		"id": "pencolor"
	},
	{
		"url": "content/help/properties/penContact.html",
		"name": "Pen Contact",
		"id": "pencontact"
	},
	{
		"url": "content/help/properties/penSize.html",
		"name": "Pen Size",
		"id": "pensize"
	},
	{
		"url": "content/help/properties/positionX.html",
		"name": "Position X",
		"id": "positionx"
	},
	{
		"url": "content/help/properties/positionY.html",
		"name": "Position Y",
		"id": "positiony"
	},
	{
		"url": "content/help/properties/positionZ.html",
		"name": "Position Z",
		"id": "positionz"
	},
	{
		"url": "content/help/features/pdf-exporter.html",
		"name": "PDF Exporter",
		"id": "pdf-exporter"
	},
	{
		"url": "content/help/features/point-cloud-exporter.html",
		"name": "Point Cloud Exporter",
		"id": "point-cloud-exporter"
	},
	{
		"url": "content/help/features/postscript-exporter.html",
		"name": "PostScript Exporter",
		"id": "postscript-exporter"
	},
	{
		"url": "content/help/properties/screenColor.html",
		"name": "Screen Color",
		"id": "screencolor"
	},
	{
		"url": "content/help/features/set-animation-time.html",
		"name": "Set -> Animation Time",
		"id": "set-animation-time"
	},
	{
		"url": "content/help/features/shapes-explorer.html",
		"name": "Shapes Explorer",
		"id": "shapes-explorer"
	},
	{
		"url": "content/help/logo-language-topics/spread-methods.html",
		"name": "Spread Methods",
		"id": "spread-methods"
	},
	{
		"url": "content/help/features/status.html",
		"name": "Status",
		"id": "status"
	},
	{
		"url": "content/help/features/string-art-template.html",
		"name": "String Art Template Drawing Exporter",
		"id": "string-art-template"
	},
	{
		"url": "content/help/tainted-images.html",
		"name": "Tainted Images",
		"id": "tainted-images"
	},
	{
		"url": "content/help/properties/turtleHeading.html",
		"name": "Turtle Heading",
		"id": "turtleheading"
	},
	{
		"url": "content/help/properties/turtleVisibility.html",
		"name": "Turtle Visibility",
		"id": "turtlevisibility"
	}
]